{"-3": {"у + GEN": ["Кто- то в драматургии нащупал тип современного интеллектуала: зубы, как У АКУЛЫ, БЛЕСТЯТ крупнейшими остротами, плечи-- сочленения тяжелейших мускулов, мраморная, в роденовском духе голова( фуга Баха и, конечно, e= mc 2), ноги изогнуты в твисте( ничто молодёжное нам не чуждо), ладони открыты морю и Аэрофлоту."]}, "-2": {"в/во + LOC": ["Раздвинулся занавес, В ГЛУБИНЕ БЛЕСТЕЛ какой-то никелированный снаряд."], "у + GEN": ["И глаза У НЕЁ БЛЕСТЯТ."]}, "-1": {"NOM": ["Весь из мускулов, ОН БЛЕСТЕЛ, как маслом облитый.", "Шумел океан, ясные и крупные ЗВЁЗДЫ БЛЕСТЕЛИ в вышине, ухала в темноте какая-то птица.", "Лошадиный стоял, рот у него был полуоткрыт, ЗУБЫ БЛЕСТЕЛИ.", "Потому что ОНА БЛЕСТЕЛА."]}, "0": {}, "1": {"NOM": ["Раздвинулся занавес, в глубине БЛЕСТЕЛ КАКОЙ-ТО никелированный снаряд.", "-- Ох, как БЛЕСТИТ ПОЛ!"], "INST": ["Полицейские вели его туда, где БЛЕСТЕЛА КРАСНЫМ лаком закрытая машина с решётками на окнах.", "Кто- то в драматургии нащупал тип современного интеллектуала: зубы, как у акулы, БЛЕСТЯТ КРУПНЕЙШИМИ остротами, плечи-- сочленения тяжелейших мускулов, мраморная, в роденовском духе голова( фуга Баха и, конечно, e= mc 2), ноги изогнуты в твисте( ничто молодёжное нам не чуждо), ладони открыты морю и Аэрофлоту."], "на + LOC": ["Теперь брюки внизу порвались и замахрились, и пиджак коробился и БЛЕСТЕЛ НА СПИНЕ и локтях."], "в/во + LOC": ["Шумел океан, ясные и крупные звёзды БЛЕСТЕЛИ В ВЫШИНЕ, ухала в темноте какая-то птица."]}, "2": {}, "3": {}}