{"-3": {"к + DAT": ["Слегка поерзал, прилаживаясь К МЕСТНОСТИ, ВЫСУНУЛ хоботок и стал просовывать его между порами."], "с/со + GEN": ["Женщина срывается С ПОСТЕЛИ-- ВЫСУНУВ голову в дверь, она цыкнула на малыша; и притворяет дверь плотнее."]}, "-2": {}, "-1": {"ACC": ["И сама говорит/ НОС ВЫСУНУ/ тихо вроде и выхожу готовить на кухню."]}, "0": {}, "1": {"ACC": ["Слегка поерзал, прилаживаясь к местности, ВЫСУНУЛ ХОБОТОК и стал просовывать его между порами.", "Женщина срывается с постели-- ВЫСУНУВ ГОЛОВУ в дверь, она цыкнула на малыша; и притворяет дверь плотнее.", "Угловая дверь с матовыми стёклами распахнута; на пороге стоит наглая Морская Девушка, ухмыляется, подмигивает Алексею Петровичу; вся набекрень; пыхает Табаком, ВЫСУНУЛА НОГУ, расставила сети: не хочешь ли попасться, а?", "Он ВЫСУНУЛ ЯЗЫК."], "из + GEN": ["Должно быть, я слишком неосторожно ВЫСУНУЛ ИЗ ТРАВЫ голову, потому что кто-то из пиратов в страхе закричал:"]}, "2": {"в/во + ACC": ["Женщина срывается с постели-- ВЫСУНУВ голову В ДВЕРЬ, она цыкнула на малыша; и притворяет дверь плотнее."]}, "3": {}}