{"-3": {"среди + GEN": ["СРЕДИ НОЧИ она ЖАРИЛА ему яичницу на электроплитке, и они поочерёдно макали хлеб в растопленное на сковородке сало."], "на + LOC": ["В лесу стемнело, но вход в пещеру освещался розовыми отблесками костра, НА КОТОРОМ Мила ЖАРИЛА пойманную Юркой птицу."]}, "-2": {}, "-1": {"NOM": ["Среди ночи ОНА ЖАРИЛА ему яичницу на электроплитке, и они поочерёдно макали хлеб в растопленное на сковородке сало.", "В лесу стемнело, но вход в пещеру освещался розовыми отблесками костра, на котором МИЛА ЖАРИЛА пойманную Юркой птицу.", "Мила и ЮРКА ЖАРИЛИ на вертеле куски мяса."], "ACC": ["Всю НОЧЬ ЖАРИЛИ и ели."]}, "0": {}, "1": {"DAT": ["Среди ночи она ЖАРИЛА ЕМУ яичницу на электроплитке, и они поочерёдно макали хлеб в растопленное на сковородке сало."], "ACC": ["Я хорошо умею ЖАРИТЬ РЫБУ.", "В лесу стемнело, но вход в пещеру освещался розовыми отблесками костра, на котором Мила ЖАРИЛА ПОЙМАННУЮ Юркой птицу.", "ЖАРЯТ ЧЕБУРЕКИ тут же, в ларьке, в чане с кипящим маслом.", "Приходим в роту/ там тоже ЖАРИМ ГРИБЫ.", "А эти женщины у них... у них в Неаполе/ э... готовят они все на улице/ такие жаровни/ и на жаровне они... ЖАРЯТ ЭТИ любимые сардинки/ от которых э... несёт этот... плохое масло очень/ вонь ужаснейшая."], "на + LOC": ["Мила и Юрка ЖАРИЛИ НА ВЕРТЕЛЕ куски мяса."]}, "2": {}, "3": {"на + LOC": ["Среди ночи она ЖАРИЛА ему яичницу НА ЭЛЕКТРОПЛИТКЕ, и они поочерёдно макали хлеб в растопленное на сковородке сало."]}}