{"-3": {}, "-2": {}, "-1": {"NOM": ["-- Да, у бабушки в старости была плохая память, и чтобы не забыть чего-нибудь, ОНА ЗАВЯЗЫВАЛА на платке узелок.", "Завязал точно так же, как Я ЗАВЯЗЫВАЮ шнурки..."], "ACC": ["Он ИХ ЗАВЯЗЫВАЛ..., делал движение, которое я отчётливо себе представляю."]}, "0": {}, "1": {"INST": ["Ее она тут же ЗАВЯЗЫВАЛА ПОЛОТЕНЦЕМ, чтобы не остыли мокрые волосы."], "ACC": ["Вошёл дежурный врач, ЗАВЯЗЫВАЯ ХАЛАТ на рукавах.", "Между тем рёв пожарных сирен оглашал округу, и покидавшие кинотеатр\" Полёт\" граждане, ещё в дурмане просмотренного фильма, ничего не слышали, медленно вытекая из зала, и Гастев смешался с ними, наклонился, будто ЗАВЯЗЫВАЯ ШНУРКИ, и подобрал валявшийся билет.", "Завязал точно так же, как я ЗАВЯЗЫВАЮ ШНУРКИ..."], "на + LOC": ["-- Да, у бабушки в старости была плохая память, и чтобы не забыть чего-нибудь, она ЗАВЯЗЫВАЛА НА ПЛАТКЕ узелок."]}, "2": {"на + LOC": ["Вошёл дежурный врач, ЗАВЯЗЫВАЯ халат НА РУКАВАХ."]}, "3": {}}