{"-3": {}, "-2": {}, "-1": {"NOM": ["Потому что сам ОН ЗАПАССЯ."], "INST": ["Вода, кроме вёдер, была налита в кастрюли, кастрюльки и бидоны, потому что старикам стало тяжело ходить к колодцу, и они пользовались СЛУЧАЕМ ЗАПАСТИСЬ водою впрок-- насколько это было возможно."]}, "0": {}, "1": {"INST": ["Вода, кроме вёдер, была налита в кастрюли, кастрюльки и бидоны, потому что старикам стало тяжело ходить к колодцу, и они пользовались случаем ЗАПАСТИСЬ ВОДОЮ впрок-- насколько это было возможно.", "Также стоит ЗАПАСТИСЬ УНИВЕРСАЛЬНОЙ затычкой для ванны\"..."]}, "2": {}, "3": {"для + GEN": ["Также стоит ЗАПАСТИСЬ универсальной затычкой ДЛЯ ВАННЫ\"..."]}}