{"-3": {}, "-2": {"на + ACC": ["Пока мы смотрели НА НЕГО ЗАТАИВ дыхание, он пружинистым движением тела слегка раскачивал перекладину."]}, "-1": {"GEN": ["Люди ПЛЕМЕНИ ЗАТАИЛИ дыхание."]}, "0": {}, "1": {"ACC": ["ЗАТАИВ ДЫХАНИЕ дожидалась у раскрытой тетрадки с домашним заданием первоклассница Кроха.", "Пока мы смотрели на него ЗАТАИВ ДЫХАНИЕ, он пружинистым движением тела слегка раскачивал перекладину.", "Он ЗАТАИЛ ДЫХАНИЕ.", "ЗАТАИВ ДЫХАНИЕ, я видел, как она наклонилась над Рыжим Псом.", "Люди племени ЗАТАИЛИ ДЫХАНИЕ."], "в/во + LOC": ["Ни у кого из тех, кто жил под угрозой камня, не было силы с ним справиться, и камень лежал так, может, сотни лет, ЗАТАИВ В СЕБЕ молчаливую угрозу людям."]}, "2": {}, "3": {"у + GEN": ["ЗАТАИВ дыхание дожидалась У РАСКРЫТОЙ тетрадки с домашним заданием первоклассница Кроха."]}}