{"-3": {"на + LOC": ["И нам хорошо-- подъехал НА ЛОШАДИ и КАТАЙ себе вниз что вяленое мясо, что сыр, что чурек\"."]}, "-2": {}, "-1": {"NOM": ["Анук ЭМЕ КАТАЛА хлебный шарик.", "Мужчин, КОТОРЫЕ КАТАЛИ короткую программу уже после открытия, было тоже 18."], "ACC": ["А вы, кажись, приехали длинный РУБЛЬ КАТАТЬ?", "Он всех НАС КАТАЛ тогда вокруг дома, а после этого сфотографировал на крыльце."]}, "0": {}, "1": {"ACC": ["Анук Эме КАТАЛА ХЛЕБНЫЙ шарик.", "-- Эх, брат, где я только не КАТАЛ ЭТОТ твой рублик!-- отвлеченно сказал\" романтик\", и тень атлантической тучки прошла по его лицу.", "Мужчин, которые КАТАЛИ КОРОТКУЮ программу уже после открытия, было тоже 18."]}, "2": {"вокруг + GEN": ["Он всех нас КАТАЛ тогда ВОКРУГ ДОМА, а после этого сфотографировал на крыльце."]}, "3": {}}