{"-3": {"в/во + LOC": ["Глава одиннадцатая, В КОТОРОЙ пираты ОСАЖДАЮТ нашу пещеру"]}, "-2": {}, "-1": {"NOM": ["Глава одиннадцатая, в которой ПИРАТЫ ОСАЖДАЮТ нашу пещеру"], "ACC": ["Но одновременно душу ЧЕЛОВЕЧЕСКУЮ ОСАЖДАЮТ демоны, склоняющие её к различным грехам и радостно докладывающие о них своему князю."]}, "0": {}, "1": {"ACC": ["Глава одиннадцатая, в которой пираты ОСАЖДАЮТ НАШУ пещеру"], "NOM": ["Меня ОСАЖДАЛИ ПРИЗРАКИ.", "Но одновременно душу человеческую ОСАЖДАЮТ ДЕМОНЫ, склоняющие её к различным грехам и радостно докладывающие о них своему князю."]}, "2": {}, "3": {}}