{"-3": {"к + DAT": ["Гляжу, сюда же, К ТЕЛЕЖКЕ, ПЛЕТЁТСЯ откуда-то Николай Рубцов."]}, "-2": {}, "-1": {"NOM": ["В один из таких вечеров, когда снег уже подтаял и на дорогах была жидкая, грязная кашица, Я ПЛЕЛАСЬ вдоль улицы к дому."], "ACC": ["Надо бросить все силы на сельское хозяйство/ а у нас оно почему-то всё ВРЕМЯ ПЛЕТЁТСЯ где-то в хвосте."]}, "0": {}, "1": {"вдоль + GEN": ["В один из таких вечеров, когда снег уже подтаял и на дорогах была жидкая, грязная кашица, я ПЛЕЛАСЬ ВДОЛЬ УЛИЦЫ к дому."]}, "2": {"в/во + LOC": ["Надо бросить все силы на сельское хозяйство/ а у нас оно почему-то всё время ПЛЕТЁТСЯ где-то В ХВОСТЕ."]}, "3": {"к + DAT": ["В один из таких вечеров, когда снег уже подтаял и на дорогах была жидкая, грязная кашица, я ПЛЕЛАСЬ вдоль улицы К ДОМУ."]}}