{"-3": {"в/во + LOC": ["Благодаря чуть изогнутой форме стальных колец В БРАСЛЕТЕ часы ПРИЛЕГАЮТ к запястью как вторая кожа."]}, "-2": {"к + DAT": ["С одной стороны К РОГУ ПРИЛЕГАЕТ веретеновидная извилина, с другой-- зубчатая, а замыкает всю структуру так называемый субикулюм."]}, "-1": {"NOM": ["Благодаря чуть изогнутой форме стальных колец в браслете ЧАСЫ ПРИЛЕГАЮТ к запястью как вторая кожа."]}, "0": {}, "1": {"к + DAT": ["Благодаря чуть изогнутой форме стальных колец в браслете часы ПРИЛЕГАЮТ К ЗАПЯСТЬЮ как вторая кожа.", "Фольга не должна ПРИЛЕГАТЬ К ПРОДУКТАМ слишком плотно."], "NOM": ["С одной стороны к рогу ПРИЛЕГАЕТ ВЕРЕТЕНОВИДНАЯ извилина, с другой-- зубчатая, а замыкает всю структуру так называемый субикулюм."]}, "2": {}, "3": {}}