{"-3": {"на + LOC": ["Я бросился в спальню и, словно на льду, поскользнулся НА ПАРКЕТЕ и РАСТЯНУЛСЯ во весь рост."]}, "-2": {}, "-1": {"NOM": ["Например, сцены в зоопарке с животными, КОТОРЫЕ РАСТЯНУЛИСЬ на добрых минут пять.", "Пот льёт с меня рекой, ноги дрожат и, кажется, вот-вот согнутся и Я РАСТЯНУСЬ прямо на земле.", "Если был ущерб, то почему эта ИСТОРИЯ РАСТЯНУЛАСЬ на четыре года?", "Может быть/ ЭТО РАСТЯНЕТСЯ не на неделю/ а может/ какая-то четвёрка начнёт работать."]}, "0": {}, "1": {"на + ACC": ["Например, сцены в зоопарке с животными, которые РАСТЯНУЛИСЬ НА ДОБРЫХ минут пять.", "Слабо затрепетали над нашими головами листья деревьев, и в ту же минуту мы увидели, как с океана к берегу идёт, РАСТЯНУВШИСЬ НА НЕСКОЛЬКО километров, высокий чёрный вал.", "Если был ущерб, то почему эта история РАСТЯНУЛАСЬ НА ЧЕТЫРЕ года?", "От вас, мама и папа, зависит, чтобы оно не РАСТЯНУЛОСЬ НА ДОЛГИЕ школьные годы, а произошло как можно скорее!"], "в/во + ACC": ["Я бросился в спальню и, словно на льду, поскользнулся на паркете и РАСТЯНУЛСЯ ВО ВЕСЬ рост."], "в/во + LOC": ["Подсохшая губа с глубокой выемкой, излучающая множество мелких морщинок, РАСТЯНУЛАСЬ В НАСМЕШЛИВОЙ улыбке:"]}, "2": {"на + LOC": ["Пот льёт с меня рекой, ноги дрожат и, кажется, вот-вот согнутся и я РАСТЯНУСЬ прямо НА ЗЕМЛЕ."], "на + ACC": ["Может быть/ это РАСТЯНЕТСЯ не НА НЕДЕЛЮ/ а может/ какая-то четвёрка начнёт работать."]}, "3": {}}